takeoff_launcher/__init__.py
takeoff_launcher/conf_mgr.py
takeoff_launcher/main.py
takeoff_launcher/utils.py
takeoff_launcher/version.txt
takeoff_launcher/sdk/__init__.py
takeoff_launcher/sdk/schema.py
takeoff_launcher/sdk/takeoff.py
takeoff_launcher/sdk/utils.py
takeoff_launcher-0.0.12.dist-info/METADATA
takeoff_launcher-0.0.12.dist-info/WHEEL
takeoff_launcher-0.0.12.dist-info/entry_points.txt
takeoff_launcher-0.0.12.dist-info/top_level.txt
takeoff_launcher-0.0.12.dist-info/RECORD
