Metadata-Version: 2.1
Name: takeoff_launcher
Version: 0.0.12
Summary: Takeoff Launcher package is a python cli tool that provides a simple interface to launch Takeoff container
Author-email: TitanML <hello@titanml.co>
Requires-Dist: pydantic ==2.5.1
Requires-Dist: pydantic-settings ==2.1.0
Requires-Dist: loguru ==0.6.0
Requires-Dist: docker ==7.0.0
Requires-Dist: typer[all] ==0.9.0
Requires-Dist: inquirerpy ==0.3.4
Requires-Dist: psutil ==5.9.7
Requires-Dist: pynvml ==11.5.0
Requires-Dist: pyyaml ==6.0.1
